pybraidz_chunked_iter-0.1.0.dist-info/METADATA
pybraidz_chunked_iter-0.1.0.dist-info/WHEEL
pybraidz_chunked_iter-0.1.0.dist-info/license_files/LICENSE-APACHE
pybraidz_chunked_iter-0.1.0.dist-info/license_files/LICENSE-MIT
pybraidz_chunked_iter/__init__.py
pybraidz_chunked_iter/pybraidz_chunked_iter.abi3.so
pybraidz_chunked_iter-0.1.0.dist-info/RECORD
