Metadata-Version: 2.1
Name: pybraidz-chunked-iter
Version: 0.1.0
License-File: LICENSE-APACHE
License-File: LICENSE-MIT
Summary: Chunked iteration over tables in .braidz files
Author-email: Andrew Straw <strawman@astraw.com>
Maintainer-email: Andrew Straw <strawman@astraw.com>
License: MIT/Apache-2.0
Requires-Python: >=3.7
Project-URL: homepage, https://github.com/strawlab/strand-braid/tree/main/braidz-parser/braidz-chunked-iter/pybraidz-chunked-iter
